{
	"configurations" : 
	[
		{
			"directories" : 
			[
				{
					"build" : ".",
					"jsonFile" : "directory-.-Release-d0094a50bb2071803777.json",
					"minimumCMakeVersion" : 
					{
						"string" : "3.16"
					},
					"projectIndex" : 0,
					"source" : ".",
					"targetIndexes" : 
					[
						0,
						1,
						2
					]
				}
			],
			"name" : "Release",
			"projects" : 
			[
				{
					"directoryIndexes" : 
					[
						0
					],
					"name" : "FirstC__APP",
					"targetIndexes" : 
					[
						0,
						1,
						2
					]
				}
			],
			"targets" : 
			[
				{
					"directoryIndex" : 0,
					"id" : "FirstC__APP::@6890427a1f51a3e7e1df",
					"jsonFile" : "target-FirstC__APP-Release-b893c20b9bf0ba7c4541.json",
					"name" : "FirstC__APP",
					"projectIndex" : 0
				},
				{
					"directoryIndex" : 0,
					"id" : "FirstC__APP_autogen::@6890427a1f51a3e7e1df",
					"jsonFile" : "target-FirstC__APP_autogen-Release-8a6c53e36167e687d0e5.json",
					"name" : "FirstC__APP_autogen",
					"projectIndex" : 0
				},
				{
					"directoryIndex" : 0,
					"id" : "FirstC__APP_autogen_timestamp_deps::@6890427a1f51a3e7e1df",
					"jsonFile" : "target-FirstC__APP_autogen_timestamp_deps-Release-65bcfb14be1a44fbc1ae.json",
					"name" : "FirstC__APP_autogen_timestamp_deps",
					"projectIndex" : 0
				}
			]
		}
	],
	"kind" : "codemodel",
	"paths" : 
	{
		"build" : "F:/CODE/GIThub/C_plus_plus/FirstC++APP/cmake-build-release",
		"source" : "F:/CODE/GIThub/C_plus_plus/FirstC++APP"
	},
	"version" : 
	{
		"major" : 2,
		"minor" : 6
	}
}
